Workbook

Sheet Raw Data
A1: WALMART | B1: 2021 | C1: 2022 | D1: 2023 | E1: 2024 | F1: 2025
B2: C$ in millions
A3: Income Statement
A4: Revenue | B4: 559151 | C4: 572754 | D4: 611289 | E4: 648125 | F4: 680985
A5: Cost of Sales | B5: 420315 | C5: 429000 | D5: 463721 | E5: 490142 | F5: 511753
A6: Gross Profit | B6: 138836 | C6: 143754 | D6: 147568 | E6: 157983 | F6: 169232
A7: Operating Income | B7: 22548 | C7: 25942 | D7: 20428 | E7: 27012 | F7: 29348
A8: Interest Expense (or Net Finance Costs) | B8: 2194 | C8: 1836 | D8: 1874 | E8: 2137 | F8: 2245
A9: Income Before Tax | B9: 20564 | C9: 18696 | D9: 17016 | E9: 21848 | F9: 26309
A10: Income Tax Expense | B10: 6858 | C10: 4756 | D10: 5724 | E10: 5578 | F10: 6152
A11: Net Income | B11: 13706 | C11: 13940 | D11: 11292 | E11: 16270 | F11: 20157
A13: Balance Sheet – Assets
A14: Cash & Cash Equivalents | B14: 17741 | C14: 14760 | D14: 8625 | E14: 9867 | F14: 9037
A15: Trade Receivables | B15: 6516 | C15: 8280 | D15: 7933 | E15: 8796 | F15: 9975
A16: Inventory | B16: 44949 | C16: 56511 | D16: 56576 | E16: 54892 | F16: 56435
A17: Total Current Assets | B17: 90067 | C17: 81070 | D17: 75655 | E17: 76877 | F17: 79458
A18: Property & Equipment (Net PPE) | B18: 92201 | C18: 94515 | D18: 100760 | E18: 110810 | F18: 119993
A19: Goodwill | B19: 28983 | C19: 29014 | D19: 28174 | E19: 28113 | F19: 28792
A20: Total Assets | B20: 252496 | C20: 244860 | D20: 243197 | E20: 252399 | F20: 260823
A22: Balance Sheet – Liabilities
A23: Accounts Payable | B23: 49141 | C23: 55261 | D23: 53742 | E23: 56812 | F23: 58666
A24: Short-Term Borrowings (if shown) | B24: 224 | C24: 410 | D24: 372 | E24: 878 | F24: 3068
A25: Current Portion of Long-Term Debt | B25: 3115 | C25: 2803 | D25: 4191 | E25: 3447 | F25: 2598
A26: Total Current Liabilities | B26: 92645 | C26: 87379 | D26: 92198 | E26: 92415 | F26: 96584
A27: Long-Term Debt | B27: 41194 | C27: 34864 | D27: 34649 | E27: 36132 | F27: 33401
A28: Total Liabilities | B28: 164965 | C28: 152969 | D28: 159443 | E28: 162050 | F28: 163402
A30: Balance Sheet – Equity
A31: Retained Earnings | B31: 88763 | C31: 86904 | D31: 83135 | E31: 89814 | F31: 98313
A32: Total Shareholders’ Equity | B32: 80925 | C32: 83253 | D32: 76693 | E32: 83861 | F32: 91013
A33: Total Equity | B33: 87531 | C33: 91891 | D33: 83754 | E33: 90349 | F33: 97421
A35: Cash Flow Statement
A36: Cash From Operating Activities | B36: 36074 | C36: 24181 | D36: 28841 | E36: 35726 | F36: 36443
A37: Capital Expenditures | B37: -10264 | C37: -13106 | D37: -16857 | E37: -20606 | F37: -23783
A38: Depreciation Expense | B38: 11152 | C38: 10658 | D38: 10945 | E38: 11853 | F38: 12973
A39: Dividends Paid | B39: -6116 | C39: -6152 | D39: -6114 | E39: -6140 | F39: -6688
A41: PPE Note
A42: Gross PPE | B42: 180571 | C42: 189324 | D42: 202370 | E42: 219859 | F42: 231617
A43: Accumulated Depreciation | B43: -88370 | C43: -94809 | D43: -101610 | E43: -109049 | F43: -111624
A44: Net PPE | B44: 92201 | C44: 94515 | D44: 100760 | E44: 110810 | F44: 119993

Sheet Ratio Analysis
A1: Walmart Ratio | B1: 2021 | C1: 2022 | D1: 2023 | E1: 2024 | F1: 2025
A2: Growth
A3: Revenue Growth | C3: ='Raw Data'!C$4/'Raw Data'!B$4-1 -> 0.024327954 | D3: ='Raw Data'!D$4/'Raw Data'!C$4-1 -> 0.067280194 | E3: ='Raw Data'!E$4/'Raw Data'!D$4-1 -> 0.06025955 | F3: ='Raw Data'!F$4/'Raw Data'!E$4-1 -> 0.050700096
A4: Profitability
A5: Gross Margin | B5: ='Raw Data'!B$6/'Raw Data'!B$4 -> 0.24829787 | C5: ='Raw Data'!C$6/'Raw Data'!C$4 -> 0.25098733 | D5: ='Raw Data'!D$6/'Raw Data'!D$4 -> 0.24140464 | E5: ='Raw Data'!E$6/'Raw Data'!E$4 -> 0.24375391 | F5: ='Raw Data'!F$6/'Raw Data'!F$4 -> 0.24851061
A6: Operating Margin | B6: ='Raw Data'!B$7/'Raw Data'!B$4 -> 0.040325422 | C6: ='Raw Data'!C$7/'Raw Data'!C$4 -> 0.045293442 | D6: ='Raw Data'!D$7/'Raw Data'!D$4 -> 0.033417909 | E6: ='Raw Data'!E$7/'Raw Data'!E$4 -> 0.041677146 | F6: ='Raw Data'!F$7/'Raw Data'!F$4 -> 0.043096397
A7: Net Margin | B7: ='Raw Data'!B$11/'Raw Data'!B$4 -> 0.024512162 | C7: ='Raw Data'!C$11/'Raw Data'!C$4 -> 0.024338547 | D7: ='Raw Data'!D$11/'Raw Data'!D$4 -> 0.018472441 | E7: ='Raw Data'!E$11/'Raw Data'!E$4 -> 0.025103182 | F7: ='Raw Data'!F$11/'Raw Data'!F$4 -> 0.029599771
A8: ROA | C8: ='Raw Data'!C$11/AVERAGE('Raw Data'!C$20,'Raw Data'!B$20) -> 0.056056426 | D8: ='Raw Data'!D$11/AVERAGE('Raw Data'!D$20,'Raw Data'!C$20) -> 0.046273284 | E8: ='Raw Data'!E$11/AVERAGE('Raw Data'!E$20,'Raw Data'!D$20) -> 0.065658318 | F8: ='Raw Data'!F$11/AVERAGE('Raw Data'!F$20,'Raw Data'!E$20) -> 0.078550803
A9: ROE | C9: ='Raw Data'!C$11/AVERAGE('Raw Data'!C$33,'Raw Data'!B$33) -> 0.15538786 | D9: ='Raw Data'!D$11/AVERAGE('Raw Data'!D$33,'Raw Data'!C$33) -> 0.12857753 | E9: ='Raw Data'!E$11/AVERAGE('Raw Data'!E$33,'Raw Data'!D$33) -> 0.18690086 | F9: ='Raw Data'!F$11/AVERAGE('Raw Data'!F$33,'Raw Data'!E$33) -> 0.21469883
A10: Liquidity
A11: Current Ratio | B11: ='Raw Data'!B$17/'Raw Data'!B$26 -> 0.97217335 | C11: ='Raw Data'!C$17/'Raw Data'!C$26 -> 0.9277973 | D11: ='Raw Data'!D$17/'Raw Data'!D$26 -> 0.82057095 | E11: ='Raw Data'!E$17/'Raw Data'!E$26 -> 0.83186712 | F11: ='Raw Data'!F$17/'Raw Data'!F$26 -> 0.82268285
A12: Quick Ratio | B12: =('Raw Data'!B$14+'Raw Data'!B$15)/'Raw Data'!B$26 -> 0.26182741 | C12: =('Raw Data'!C$14+'Raw Data'!C$15)/'Raw Data'!C$26 -> 0.26367892 | D12: =('Raw Data'!D$14+'Raw Data'!D$15)/'Raw Data'!D$26 -> 0.17959175 | E12: =('Raw Data'!E$14+'Raw Data'!E$15)/'Raw Data'!E$26 -> 0.20194774 | F12: =('Raw Data'!F$14+'Raw Data'!F$15)/'Raw Data'!F$26 -> 0.1968442
A13: Solvency
A14: Debt Ratio | B14: ='Raw Data'!B$28/'Raw Data'!B$20 -> 0.65333708 | C14: ='Raw Data'!C$28/'Raw Data'!C$20 -> 0.62472025 | D14: ='Raw Data'!D$28/'Raw Data'!D$20 -> 0.65561253 | E14: ='Raw Data'!E$28/'Raw Data'!E$20 -> 0.64203899 | F14: ='Raw Data'!F$28/'Raw Data'!F$20 -> 0.62648616
A15: Debt-to-Equity | B15: ='Raw Data'!B$28/'Raw Data'!B$33 -> 1.8846466 | C15: ='Raw Data'!C$28/'Raw Data'!C$33 -> 1.6646788 | D15: ='Raw Data'!D$28/'Raw Data'!D$33 -> 1.9037061 | E15: ='Raw Data'!E$28/'Raw Data'!E$33 -> 1.7936004 | F15: ='Raw Data'!F$28/'Raw Data'!F$33 -> 1.677277
A16: Efficiency
A17: Asset Turnover | C17: ='Raw Data'!C$4/AVERAGE('Raw Data'!C$20,'Raw Data'!B$20) -> 2.3031953 | D17: ='Raw Data'!D$4/AVERAGE('Raw Data'!D$20,'Raw Data'!C$20) -> 2.5049902 | E17: ='Raw Data'!E$4/AVERAGE('Raw Data'!E$20,'Raw Data'!D$20) -> 2.6155377 | F17: ='Raw Data'!F$4/AVERAGE('Raw Data'!F$20,'Raw Data'!E$20) -> 2.6537639
A18: Inventory Turnover | C18: ='Raw Data'!C$5/AVERAGE('Raw Data'!C$16,'Raw Data'!B$16) -> 8.4565346 | D18: ='Raw Data'!D$5/AVERAGE('Raw Data'!D$16,'Raw Data'!C$16) -> 8.2011372 | E18: ='Raw Data'!E$5/AVERAGE('Raw Data'!E$16,'Raw Data'!D$16) -> 8.7943087 | F18: ='Raw Data'!F$5/AVERAGE('Raw Data'!F$16,'Raw Data'!E$16) -> 9.1936907
A19: Cash Flow
A20: OCF / Net Income | B20: ='Raw Data'!B$36/'Raw Data'!B$11 -> 2.631986 | C20: ='Raw Data'!C$36/'Raw Data'!C$11 -> 1.7346485 | D20: ='Raw Data'!D$36/'Raw Data'!D$11 -> 2.5541091 | E20: ='Raw Data'!E$36/'Raw Data'!E$11 -> 2.1958205 | F20: ='Raw Data'!F$36/'Raw Data'!F$11 -> 1.8079575
A21: Free Cash Flow | B21: ='Raw Data'!B$36-ABS('Raw Data'!B$37) -> 25810 | C21: ='Raw Data'!C$36-ABS('Raw Data'!C$37) -> 11075 | D21: ='Raw Data'!D$36-ABS('Raw Data'!D$37) -> 11984 | E21: ='Raw Data'!E$36-ABS('Raw Data'!E$37) -> 15120 | F21: ='Raw Data'!F$36-ABS('Raw Data'!F$37) -> 12660

Sheet Trend Analysis
A1: Walmart YoY Change | B1: 2021 | C1: 2022 | D1: 2023 | E1: 2024 | F1: 2025
A2: Revenue | C2: ='Raw Data'!C$4-'Raw Data'!B$4 -> 13603 | D2: ='Raw Data'!D$4-'Raw Data'!C$4 -> 38535 | E2: ='Raw Data'!E$4-'Raw Data'!D$4 -> 36836 | F2: ='Raw Data'!F$4-'Raw Data'!E$4 -> 32860
A3: Gross Profit | C3: ='Raw Data'!C$6-'Raw Data'!B$6 -> 4918 | D3: ='Raw Data'!D$6-'Raw Data'!C$6 -> 3814 | E3: ='Raw Data'!E$6-'Raw Data'!D$6 -> 10415 | F3: ='Raw Data'!F$6-'Raw Data'!E$6 -> 11249
A4: Operating Income | C4: ='Raw Data'!C$7-'Raw Data'!B$7 -> 3394 | D4: ='Raw Data'!D$7-'Raw Data'!C$7 -> -5514 | E4: ='Raw Data'!E$7-'Raw Data'!D$7 -> 6584 | F4: ='Raw Data'!F$7-'Raw Data'!E$7 -> 2336
A5: Net Income | C5: ='Raw Data'!C$11-'Raw Data'!B$11 -> 234 | D5: ='Raw Data'!D$11-'Raw Data'!C$11 -> -2648 | E5: ='Raw Data'!E$11-'Raw Data'!D$11 -> 4978 | F5: ='Raw Data'!F$11-'Raw Data'!E$11 -> 3887
A6: Total Assets | C6: ='Raw Data'!C$20-'Raw Data'!B$20 -> -7636 | D6: ='Raw Data'!D$20-'Raw Data'!C$20 -> -1663 | E6: ='Raw Data'!E$20-'Raw Data'!D$20 -> 9202 | F6: ='Raw Data'!F$20-'Raw Data'!E$20 -> 8424
A7: Total Liabilities | C7: ='Raw Data'!C$28-'Raw Data'!B$28 -> -11996 | D7: ='Raw Data'!D$28-'Raw Data'!C$28 -> 6474 | E7: ='Raw Data'!E$28-'Raw Data'!D$28 -> 2607 | F7: ='Raw Data'!F$28-'Raw Data'!E$28 -> 1352
A8: Total Equity | C8: ='Raw Data'!C$33-'Raw Data'!B$33 -> 4360 | D8: ='Raw Data'!D$33-'Raw Data'!C$33 -> -8137 | E8: ='Raw Data'!E$33-'Raw Data'!D$33 -> 6595 | F8: ='Raw Data'!F$33-'Raw Data'!E$33 -> 7072
A9: Inventory | C9: ='Raw Data'!C$16-'Raw Data'!B$16 -> 11562 | D9: ='Raw Data'!D$16-'Raw Data'!C$16 -> 65 | E9: ='Raw Data'!E$16-'Raw Data'!D$16 -> -1684 | F9: ='Raw Data'!F$16-'Raw Data'!E$16 -> 1543
A10: Cash From Operating Activities | C10: ='Raw Data'!C$36-'Raw Data'!B$36 -> -11893 | D10: ='Raw Data'!D$36-'Raw Data'!C$36 -> 4660 | E10: ='Raw Data'!E$36-'Raw Data'!D$36 -> 6885 | F10: ='Raw Data'!F$36-'Raw Data'!E$36 -> 717
A11: Gross PPE | C11: ='Raw Data'!C$42-'Raw Data'!B$42 -> 8753 | D11: ='Raw Data'!D$42-'Raw Data'!C$42 -> 13046 | E11: ='Raw Data'!E$42-'Raw Data'!D$42 -> 17489 | F11: ='Raw Data'!F$42-'Raw Data'!E$42 -> 11758
A12: Net PPE | C12: ='Raw Data'!C$44-'Raw Data'!B$44 -> 2314 | D12: ='Raw Data'!D$44-'Raw Data'!C$44 -> 6245 | E12: ='Raw Data'!E$44-'Raw Data'!D$44 -> 10050 | F12: ='Raw Data'!F$44-'Raw Data'!E$44 -> 9183

Sheet Common-Size Income Statement
A1: Walmart Common-Size Income Statement | B1: 2021 | C1: 2022 | D1: 2023 | E1: 2024 | F1: 2025
A2: Revenue | B2: =1 -> 1 | C2: =1 -> 1 | D2: =1 -> 1 | E2: =1 -> 1 | F2: =1 -> 1
A3: Cost of Sales | B3: ='Raw Data'!B$5/'Raw Data'!B$4 -> 0.75170213 | C3: ='Raw Data'!C$5/'Raw Data'!C$4 -> 0.74901267 | D3: ='Raw Data'!D$5/'Raw Data'!D$4 -> 0.75859536 | E3: ='Raw Data'!E$5/'Raw Data'!E$4 -> 0.75624609 | F3: ='Raw Data'!F$5/'Raw Data'!F$4 -> 0.75148939
A4: Gross Profit | B4: ='Raw Data'!B$6/'Raw Data'!B$4 -> 0.24829787 | C4: ='Raw Data'!C$6/'Raw Data'!C$4 -> 0.25098733 | D4: ='Raw Data'!D$6/'Raw Data'!D$4 -> 0.24140464 | E4: ='Raw Data'!E$6/'Raw Data'!E$4 -> 0.24375391 | F4: ='Raw Data'!F$6/'Raw Data'!F$4 -> 0.24851061
A5: Operating Income | B5: ='Raw Data'!B$7/'Raw Data'!B$4 -> 0.040325422 | C5: ='Raw Data'!C$7/'Raw Data'!C$4 -> 0.045293442 | D5: ='Raw Data'!D$7/'Raw Data'!D$4 -> 0.033417909 | E5: ='Raw Data'!E$7/'Raw Data'!E$4 -> 0.041677146 | F5: ='Raw Data'!F$7/'Raw Data'!F$4 -> 0.043096397
A6: Interest Expense (or Net Finance Costs) | B6: ='Raw Data'!B$8/'Raw Data'!B$4 -> 0.0039238059 | C6: ='Raw Data'!C$8/'Raw Data'!C$4 -> 0.0032055647 | D6: ='Raw Data'!D$8/'Raw Data'!D$4 -> 0.0030656531 | E6: ='Raw Data'!E$8/'Raw Data'!E$4 -> 0.0032972035 | F6: ='Raw Data'!F$8/'Raw Data'!F$4 -> 0.0032966952
A7: Income Before Tax | B7: ='Raw Data'!B$9/'Raw Data'!B$4 -> 0.036777185 | C7: ='Raw Data'!C$9/'Raw Data'!C$4 -> 0.032642286 | D7: ='Raw Data'!D$9/'Raw Data'!D$4 -> 0.027836261 | E7: ='Raw Data'!E$9/'Raw Data'!E$4 -> 0.033709547 | F7: ='Raw Data'!F$9/'Raw Data'!F$4 -> 0.038633744
A8: Income Tax Expense | B8: ='Raw Data'!B$10/'Raw Data'!B$4 -> 0.012265023 | C8: ='Raw Data'!C$10/'Raw Data'!C$4 -> 0.0083037395 | D8: ='Raw Data'!D$10/'Raw Data'!D$4 -> 0.0093638197 | E8: ='Raw Data'!E$10/'Raw Data'!E$4 -> 0.0086063645 | F8: ='Raw Data'!F$10/'Raw Data'!F$4 -> 0.0090339728
A9: Net Income | B9: ='Raw Data'!B$11/'Raw Data'!B$4 -> 0.024512162 | C9: ='Raw Data'!C$11/'Raw Data'!C$4 -> 0.024338547 | D9: ='Raw Data'!D$11/'Raw Data'!D$4 -> 0.018472441 | E9: ='Raw Data'!E$11/'Raw Data'!E$4 -> 0.025103182 | F9: ='Raw Data'!F$11/'Raw Data'!F$4 -> 0.029599771

Sheet PPE Analysis
A1: PPE Analysis | B1: 2021 | C1: 2022 | D1: 2023 | E1: 2024 | F1: 2025
A2: Gross PPE | B2: ='Raw Data'!B$42 -> 180571 | C2: ='Raw Data'!C$42 -> 189324 | D2: ='Raw Data'!D$42 -> 202370 | E2: ='Raw Data'!E$42 -> 219859 | F2: ='Raw Data'!F$42 -> 231617
A3: Accumulated Depreciation | B3: ='Raw Data'!B$43 -> -88370 | C3: ='Raw Data'!C$43 -> -94809 | D3: ='Raw Data'!D$43 -> -101610 | E3: ='Raw Data'!E$43 -> -109049 | F3: ='Raw Data'!F$43 -> -111624
A4: Net PPE | B4: ='Raw Data'!B$44 -> 92201 | C4: ='Raw Data'!C$44 -> 94515 | D4: ='Raw Data'!D$44 -> 100760 | E4: ='Raw Data'!E$44 -> 110810 | F4: ='Raw Data'!F$44 -> 119993
A5: Net PPE / Total Assets | B5: ='Raw Data'!B$44/'Raw Data'!B$20 -> 0.36515826 | C5: ='Raw Data'!C$44/'Raw Data'!C$20 -> 0.38599608 | D5: ='Raw Data'!D$44/'Raw Data'!D$20 -> 0.41431432 | E5: ='Raw Data'!E$44/'Raw Data'!E$20 -> 0.4390271 | F5: ='Raw Data'!F$44/'Raw Data'!F$20 -> 0.46005529
A6: Accumulated Depreciation / Gross PPE | B6: =ABS('Raw Data'!B$43)/'Raw Data'!B$42 -> 0.48939198 | C6: =ABS('Raw Data'!C$43)/'Raw Data'!C$42 -> 0.50077645 | D6: =ABS('Raw Data'!D$43)/'Raw Data'!D$42 -> 0.50210011 | E6: =ABS('Raw Data'!E$43)/'Raw Data'!E$42 -> 0.49599516 | F6: =ABS('Raw Data'!F$43)/'Raw Data'!F$42 -> 0.48193354
A7: Capital Expenditures / Revenue | B7: =ABS('Raw Data'!B$37)/'Raw Data'!B$4 -> 0.018356401 | C7: =ABS('Raw Data'!C$37)/'Raw Data'!C$4 -> 0.022882424 | D7: =ABS('Raw Data'!D$37)/'Raw Data'!D$4 -> 0.027576155 | E7: =ABS('Raw Data'!E$37)/'Raw Data'!E$4 -> 0.03179325 | F7: =ABS('Raw Data'!F$37)/'Raw Data'!F$4 -> 0.034924411
A8: Depreciation Expense / Gross PPE | B8: ='Raw Data'!B$38/'Raw Data'!B$42 -> 0.06175964 | C8: ='Raw Data'!C$38/'Raw Data'!C$42 -> 0.056295029 | D8: ='Raw Data'!D$38/'Raw Data'!D$42 -> 0.054084103 | E8: ='Raw Data'!E$38/'Raw Data'!E$42 -> 0.053911825 | F8: ='Raw Data'!F$38/'Raw Data'!F$42 -> 0.056010569

Sheet Dashboard
A1: Summary Dashboard | B1: 2021 | C1: 2022 | D1: 2023 | E1: 2024 | F1: 2025 | H1: Trend Chart Data | I1: 2021 | J1: 2022 | K1: 2023 | L1: 2024 | M1: 2025
A2: Revenue | B2: ='Raw Data'!B$4 -> 559151 | C2: ='Raw Data'!C$4 -> 572754 | D2: ='Raw Data'!D$4 -> 611289 | E2: ='Raw Data'!E$4 -> 648125 | F2: ='Raw Data'!F$4 -> 680985 | H2: Revenue | I2: ='Raw Data'!B$4 -> 559151 | J2: ='Raw Data'!C$4 -> 572754 | K2: ='Raw Data'!D$4 -> 611289 | L2: ='Raw Data'!E$4 -> 648125 | M2: ='Raw Data'!F$4 -> 680985
A3: Net Income | B3: ='Raw Data'!B$11 -> 13706 | C3: ='Raw Data'!C$11 -> 13940 | D3: ='Raw Data'!D$11 -> 11292 | E3: ='Raw Data'!E$11 -> 16270 | F3: ='Raw Data'!F$11 -> 20157 | H3: Net Income | I3: ='Raw Data'!B$11 -> 13706 | J3: ='Raw Data'!C$11 -> 13940 | K3: ='Raw Data'!D$11 -> 11292 | L3: ='Raw Data'!E$11 -> 16270 | M3: ='Raw Data'!F$11 -> 20157
A4: Cash From Operating Activities | B4: ='Raw Data'!B$36 -> 36074 | C4: ='Raw Data'!C$36 -> 24181 | D4: ='Raw Data'!D$36 -> 28841 | E4: ='Raw Data'!E$36 -> 35726 | F4: ='Raw Data'!F$36 -> 36443 | H4: Operating Cash Flow | I4: ='Raw Data'!B$36 -> 36074 | J4: ='Raw Data'!C$36 -> 24181 | K4: ='Raw Data'!D$36 -> 28841 | L4: ='Raw Data'!E$36 -> 35726 | M4: ='Raw Data'!F$36 -> 36443
A5: Total Assets | B5: ='Raw Data'!B$20 -> 252496 | C5: ='Raw Data'!C$20 -> 244860 | D5: ='Raw Data'!D$20 -> 243197 | E5: ='Raw Data'!E$20 -> 252399 | F5: ='Raw Data'!F$20 -> 260823
A6: Total Liabilities | B6: ='Raw Data'!B$28 -> 164965 | C6: ='Raw Data'!C$28 -> 152969 | D6: ='Raw Data'!D$28 -> 159443 | E6: ='Raw Data'!E$28 -> 162050 | F6: ='Raw Data'!F$28 -> 163402 | H6: Key Ratio Chart Data | I6: 2021 | J6: 2022 | K6: 2023 | L6: 2024 | M6: 2025
A7: Gross Margin | B7: ='Ratio Analysis'!B$5 -> 0.24829787 | C7: ='Ratio Analysis'!C$5 -> 0.25098733 | D7: ='Ratio Analysis'!D$5 -> 0.24140464 | E7: ='Ratio Analysis'!E$5 -> 0.24375391 | F7: ='Ratio Analysis'!F$5 -> 0.24851061 | H7: Gross Margin | I7: ='Ratio Analysis'!B$5 -> 0.24829787 | J7: ='Ratio Analysis'!C$5 -> 0.25098733 | K7: ='Ratio Analysis'!D$5 -> 0.24140464 | L7: ='Ratio Analysis'!E$5 -> 0.24375391 | M7: ='Ratio Analysis'!F$5 -> 0.24851061
A8: Net Margin | B8: ='Ratio Analysis'!B$7 -> 0.024512162 | C8: ='Ratio Analysis'!C$7 -> 0.024338547 | D8: ='Ratio Analysis'!D$7 -> 0.018472441 | E8: ='Ratio Analysis'!E$7 -> 0.025103182 | F8: ='Ratio Analysis'!F$7 -> 0.029599771 | H8: Net Margin | I8: ='Ratio Analysis'!B$7 -> 0.024512162 | J8: ='Ratio Analysis'!C$7 -> 0.024338547 | K8: ='Ratio Analysis'!D$7 -> 0.018472441 | L8: ='Ratio Analysis'!E$7 -> 0.025103182 | M8: ='Ratio Analysis'!F$7 -> 0.029599771
A9: Current Ratio | B9: ='Ratio Analysis'!B$11 -> 0.97217335 | C9: ='Ratio Analysis'!C$11 -> 0.9277973 | D9: ='Ratio Analysis'!D$11 -> 0.82057095 | E9: ='Ratio Analysis'!E$11 -> 0.83186712 | F9: ='Ratio Analysis'!F$11 -> 0.82268285 | H9: Current Ratio | I9: ='Ratio Analysis'!B$11 -> 0.97217335 | J9: ='Ratio Analysis'!C$11 -> 0.9277973 | K9: ='Ratio Analysis'!D$11 -> 0.82057095 | L9: ='Ratio Analysis'!E$11 -> 0.83186712 | M9: ='Ratio Analysis'!F$11 -> 0.82268285
A10: Debt Ratio | B10: ='Ratio Analysis'!B$14 -> 0.65333708 | C10: ='Ratio Analysis'!C$14 -> 0.62472025 | D10: ='Ratio Analysis'!D$14 -> 0.65561253 | E10: ='Ratio Analysis'!E$14 -> 0.64203899 | F10: ='Ratio Analysis'!F$14 -> 0.62648616 | H10: Debt Ratio | I10: ='Ratio Analysis'!B$14 -> 0.65333708 | J10: ='Ratio Analysis'!C$14 -> 0.62472025 | K10: ='Ratio Analysis'!D$14 -> 0.65561253 | L10: ='Ratio Analysis'!E$14 -> 0.64203899 | M10: ='Ratio Analysis'!F$14 -> 0.62648616
